sysml/__init__.py
sysml/__src__.py
sysml/test.py
systems_modeling_language-0.1.0.dist-info/METADATA
systems_modeling_language-0.1.0.dist-info/WHEEL
systems_modeling_language-0.1.0.dist-info/top_level.txt
systems_modeling_language-0.1.0.dist-info/RECORD
